workflow_engine/__init__.py
workflow_engine/py.typed
workflow_engine/contexts/__init__.py
workflow_engine/contexts/in_memory.py
workflow_engine/contexts/local.py
workflow_engine/core/__init__.py
workflow_engine/core/context.py
workflow_engine/core/edge.py
workflow_engine/core/error.py
workflow_engine/core/execution.py
workflow_engine/core/node.py
workflow_engine/core/workflow.py
workflow_engine/core/migration/__init__.py
workflow_engine/core/migration/exceptions.py
workflow_engine/core/migration/migration.py
workflow_engine/core/migration/registry.py
workflow_engine/core/migration/runner.py
workflow_engine/core/migration/workflow_migration.py
workflow_engine/core/values/__init__.py
workflow_engine/core/values/data.py
workflow_engine/core/values/extraction.py
workflow_engine/core/values/file.py
workflow_engine/core/values/json.py
workflow_engine/core/values/mapping.py
workflow_engine/core/values/model.py
workflow_engine/core/values/primitives.py
workflow_engine/core/values/schema.py
workflow_engine/core/values/sequence.py
workflow_engine/core/values/value.py
workflow_engine/execution/__init__.py
workflow_engine/execution/parallel.py
workflow_engine/execution/rate_limit.py
workflow_engine/execution/retry.py
workflow_engine/execution/topological.py
workflow_engine/files/__init__.py
workflow_engine/files/json.py
workflow_engine/files/pdf.py
workflow_engine/files/text.py
workflow_engine/nodes/__init__.py
workflow_engine/nodes/arithmetic.py
workflow_engine/nodes/conditional.py
workflow_engine/nodes/constant.py
workflow_engine/nodes/data.py
workflow_engine/nodes/error.py
workflow_engine/nodes/iteration.py
workflow_engine/nodes/text.py
workflow_engine/utils/__init__.py
workflow_engine/utils/env.py
workflow_engine/utils/immutable.py
workflow_engine/utils/iter.py
workflow_engine/utils/mappings.py
workflow_engine/utils/semver.py
aceteam_workflow_engine-1.1.0rc1.dist-info/METADATA
aceteam_workflow_engine-1.1.0rc1.dist-info/WHEEL
aceteam_workflow_engine-1.1.0rc1.dist-info/licenses/LICENSE
aceteam_workflow_engine-1.1.0rc1.dist-info/RECORD
