Metadata-Version: 2.4
Name: aceteam-workflow-engine
Version: 1.1.0rc1
Summary: A powerful workflow orchestration engine for composing complex computational tasks from modular, type-safe nodes
Project-URL: Homepage, https://aceteam.ai/workflow-engine
Project-URL: Documentation, https://github.com/aceteam-ai/workflow-engine/tree/main/docs
Project-URL: Repository, https://github.com/aceteam-ai/workflow-engine
Project-URL: Issues, https://github.com/aceteam-ai/workflow-engine/issues
Project-URL: Changelog, https://github.com/aceteam-ai/workflow-engine/blob/main/CHANGELOG.md
Author-email: Anthony Tecsa <anthonytecsa@gmail.com>, Jason Sun <jason@adanomad.com>, Justin Xu <xu.justin.j@gmail.com>
License-Expression: MIT
License-File: LICENSE
Keywords: async,automation,dag,execution,graph,orchestration,pipeline,workflow
Classifier: Development Status :: 4 - Beta
Classifier: Framework :: Pydantic :: 2
Classifier: Intended Audience :: Developers
Classifier: License :: OSI Approved :: MIT License
Classifier: Operating System :: OS Independent
Classifier: Programming Language :: Python :: 3
Classifier: Programming Language :: Python :: 3.12
Classifier: Programming Language :: Python :: 3.13
Classifier: Topic :: Software Development :: Libraries :: Python Modules
Classifier: Typing :: Typed
Requires-Python: <4.0,>=3.12
Requires-Dist: dotenv>=0.9.9
Requires-Dist: networkx<4.0.0,>=3.4.2
Requires-Dist: overrides>=7.7.0
Requires-Dist: pydantic<3.0.0,>=2.11.1
